CONTRIBUTING.rst
MANIFEST.in
README.rst
setup.cfg
setup.py
plone/__init__.py
plone.directives.tiles.egg-info/PKG-INFO
plone.directives.tiles.egg-info/SOURCES.txt
plone.directives.tiles.egg-info/dependency_links.txt
plone.directives.tiles.egg-info/namespace_packages.txt
plone.directives.tiles.egg-info/not-zip-safe
plone.directives.tiles.egg-info/requires.txt
plone.directives.tiles.egg-info/top_level.txt
plone/directives/__init__.py
plone/directives/tiles/__init__.py
plone/directives/tiles/components.py
plone/directives/tiles/configure.zcml
plone/directives/tiles/meta.py
plone/directives/tiles/meta.zcml
plone/directives/tiles/tests/__init__.py
plone/directives/tiles/tests/test_grokker.py
plone/directives/tiles/tests/test_grokker_templates/mytile.pt