Metadata-Version: 1.1
Name: plone.directives.tiles
Version: 1.2
Summary: Grokkers for plone.tiles
Home-page: https://github.com/plone/plone.directives.tiles
Author: Martin Aspeli
Author-email: optilude@gmail.com
License: GPL
Keywords: plone tiles deco blocks grok directives
Platform: UNKNOWN
Classifier: Framework :: Plone
Classifier: Framework :: Plone :: 5.0
Classifier: Framework :: Plone :: 5.1
Classifier: Programming Language :: Python
Classifier: Programming Language :: Python :: 2.7
Classifier: Topic :: Software Development :: Libraries :: Python Modules
